openwisp_ipam/__init__.py
openwisp_ipam/admin.py
openwisp_ipam/apps.py
openwisp_ipam/filters.py
openwisp_ipam/models.py
openwisp_ipam/urls.py
openwisp_ipam/api/__init__.py
openwisp_ipam/api/responses.py
openwisp_ipam/api/serializers.py
openwisp_ipam/api/urls.py
openwisp_ipam/api/utils.py
openwisp_ipam/api/views.py
openwisp_ipam/base/__init__.py
openwisp_ipam/base/fields.py
openwisp_ipam/base/forms.py
openwisp_ipam/base/models.py
openwisp_ipam/management/__init__.py
openwisp_ipam/management/commands/__init__.py
openwisp_ipam/management/commands/export_subnet.py
openwisp_ipam/management/commands/import_subnet.py
openwisp_ipam/migrations/0001_initial.py
openwisp_ipam/migrations/0002_remove_ipaddress_organization.py
openwisp_ipam/migrations/0003_shareable_subnets.py
openwisp_ipam/migrations/0004_subnet_organization_unique_together.py
openwisp_ipam/migrations/0005_default_groups_permissions.py
openwisp_ipam/migrations/__init__.py
openwisp_ipam/static/openwisp-ipam/css/admin.css
openwisp_ipam/static/openwisp-ipam/css/minified/32px.png
openwisp_ipam/static/openwisp-ipam/css/minified/40px.png
openwisp_ipam/static/openwisp-ipam/css/minified/jstree.min.css
openwisp_ipam/static/openwisp-ipam/css/minified/throbber.gif
openwisp_ipam/static/openwisp-ipam/js/ip-request.js
openwisp_ipam/static/openwisp-ipam/js/subnet.js
openwisp_ipam/static/openwisp-ipam/js/minified/jstree.min.js
openwisp_ipam/static/openwisp-ipam/js/minified/plotly.min.js
openwisp_ipam/templates/admin/openwisp-ipam/ip_address/change_form.html
openwisp_ipam/templates/admin/openwisp-ipam/subnet/change_form.html
openwisp_ipam/templates/admin/openwisp-ipam/subnet/change_list.html
openwisp_ipam/templates/admin/openwisp-ipam/subnet/import.html
openwisp_ipam/tests/__init__.py
openwisp_ipam/tests/test_admin.py
openwisp_ipam/tests/test_api.py
openwisp_ipam/tests/test_commands.py
openwisp_ipam/tests/test_forms.py
openwisp_ipam/tests/test_models.py
openwisp_ipam/tests/test_multitenant.py
openwisp_ipam-1.2.post1.dist-info/licenses/LICENSE
openwisp_ipam-1.2.post1.dist-info/METADATA
openwisp_ipam-1.2.post1.dist-info/WHEEL
openwisp_ipam-1.2.post1.dist-info/top_level.txt
openwisp_ipam-1.2.post1.dist-info/RECORD
