Metadata-Version: 2.4
Name: openwisp-ipam
Version: 1.2.post1
Summary: IP address space administration module of OpenWISP.
Home-page: https://github.com/openwisp/openwisp-ipam
Download-URL: https://github.com/openwisp/openwisp-ipam/releases
Author: OpenWISP
Author-email: support@openwisp.io
License: BSD-3-Clause
Keywords: django,freeradius,networking,openwisp
Platform: Platform Independent
Classifier: Development Status :: 5 - Production/Stable
Classifier: Environment :: Web Environment
Classifier: Topic :: Internet :: WWW/HTTP
Classifier: Topic :: System :: Networking
Classifier: Intended Audience :: Developers
Classifier: License :: OSI Approved :: BSD License
Classifier: Operating System :: OS Independent
Classifier: Framework :: Django
Classifier: Programming Language :: Python :: 3
License-File: LICENSE
Requires-Dist: openwisp-users~=1.2.0
Requires-Dist: openwisp-utils[rest]~=1.2.0
Requires-Dist: django-reversion~=6.0.0
Requires-Dist: openpyxl~=3.1.5
Dynamic: author
Dynamic: author-email
Dynamic: classifier
Dynamic: description
Dynamic: download-url
Dynamic: home-page
Dynamic: keywords
Dynamic: license
Dynamic: license-file
Dynamic: platform
Dynamic: requires-dist
Dynamic: summary
